<?xml version="1.0" encoding="utf-8"?>
<IncrementalBankBuild Version="6" Flags="878078161">
	<Platform GUID="{675FE364-3D45-470E-B0AF-D25125C38277}">
		<Banks>
			<Language ID="393239870">
				<File Name="Init" Hash="3553573946" Timestamp="131719815040822335"/>
				<File Name="Main" Hash="177734187" Timestamp="131719815040742437"/>
			</Language>
		</Banks>
		<XMLInfo>
			<Language ID="-1">
				<File Name="" Hash="1324570116" Timestamp="131719815040842345"/>
			</Language>
		</XMLInfo>
	</Platform>
</IncrementalBankBuild>
